README.rst
setup.py
whatwhen/__init__.py
whatwhen.egg-info/PKG-INFO
whatwhen.egg-info/SOURCES.txt
whatwhen.egg-info/dependency_links.txt
whatwhen.egg-info/top_level.txt
whatwhen/tests/__init__.py