Metadata-Version: 1.1
Name: whatwhen
Version: 0.1.1
Summary: A higher-level topological sort.
Home-page: UNKNOWN
Author: Stijn Debrouwere
Author-email: stijn@debrouwere.org
License: ISC
Download-URL: http://www.github.com/debrouwere/python-whatwhen/tarball/master
Keywords: topological sort toposort topsort dependencies dependency resolver
Platform: UNKNOWN
Classifier: Development Status :: 4 - Beta
Classifier: Intended Audience :: Developers
Classifier: License :: OSI Approved :: MIT License
Classifier: Operating System :: OS Independent
Classifier: Programming Language :: Python
Classifier: Topic :: Utilities
